mssql/__init__.py
mssql/server.py
mcp_mssql-0.1.4.dist-info/LICENSE
mcp_mssql-0.1.4.dist-info/METADATA
mcp_mssql-0.1.4.dist-info/WHEEL
mcp_mssql-0.1.4.dist-info/top_level.txt
mcp_mssql-0.1.4.dist-info/RECORD
