Metadata-Version: 2.2
Name: mcp-mssql
Version: 0.1.4
Summary: MSSQL server package for MCP
Home-page: https://github.com/amornpan/mcp-mssql
Author: amornpan
Author-email: amornpan@gmail.com
Classifier: Programming Language :: Python :: 3
Classifier: License :: OSI Approved :: MIT License
Classifier: Operating System :: OS Independent
Requires-Python: >=3.6
License-File: LICENSE
Requires-Dist: anyio==4.8.0
Requires-Dist: certifi==2025.1.31
Requires-Dist: click==8.1.8
Requires-Dist: colorama==0.4.6
Requires-Dist: exceptiongroup==1.2.2
Requires-Dist: fastapi==0.115.8
Requires-Dist: h11==0.14.0
Requires-Dist: httpcore==1.0.7
Requires-Dist: httpx==0.28.1
Requires-Dist: httpx-sse==0.4.0
Requires-Dist: idna==3.10
Requires-Dist: mcp==1.2.0
Requires-Dist: pydantic==2.10.6
Requires-Dist: pydantic-settings==2.7.1
Requires-Dist: pydantic_core==2.27.2
Requires-Dist: pyodbc==5.2.0
Requires-Dist: python-dotenv==1.0.1
Requires-Dist: sniffio==1.3.1
Requires-Dist: sse-starlette==2.2.1
Requires-Dist: starlette==0.45.3
Requires-Dist: typing_extensions==4.12.2
Requires-Dist: uvicorn==0.34.0
Dynamic: author
Dynamic: author-email
Dynamic: classifier
Dynamic: description
Dynamic: description-content-type
Dynamic: home-page
Dynamic: requires-dist
Dynamic: requires-python
Dynamic: summary
